pyioweather/__init__.py
pyioweather/main.py
pyioweather-0.0.22.dist-info/METADATA
pyioweather-0.0.22.dist-info/WHEEL
pyioweather-0.0.22.dist-info/entry_points.txt
pyioweather-0.0.22.dist-info/top_level.txt
pyioweather-0.0.22.dist-info/RECORD
