Metadata-Version: 2.4
Name: pyioweather
Version: 0.0.22
Summary: A CLI tool for fetching the current weather using Tomorrow.io
Author-email: Dekoder-py <dekod3r.py@gmail.com>
License-Expression: MIT
Requires-Dist: requests
Requires-Dist: python-dotenv
Requires-Dist: rich
